{
  "SessionDuration": 0.3884942,
  "TaskResults": [
    {
      "DryRun": false,
      "Description": "Generate comprehensive HTML and text reports of all operations",
      "Output": {
        "TextReport": "C:\\Users\\Bogdan\\OneDrive\\Desktop\\Projects\\script_mentenanta\\temp_files\\session-20251014-145603\\reports\\maintenance-report-20251014-150537.txt",
        "HtmlReport": "C:\\Users\\Bogdan\\OneDrive\\Desktop\\Projects\\script_mentenanta\\temp_files\\session-20251014-145603\\reports\\maintenance-report-20251014-150537.txt",
        "ExecutionSummary": "C:\\Users\\Bogdan\\OneDrive\\Desktop\\Projects\\script_mentenanta\\temp_files\\session-20251014-145603\\reports\\execution-summary.json",
        "Duration": 0.0821211,
        "GenerationTime": "2025-10-14T15:05:38.0200469+03:00",
        "JsonExport": "C:\\Users\\Bogdan\\OneDrive\\Desktop\\Projects\\script_mentenanta\\temp_files\\session-20251014-145603\\reports\\maintenance-report-20251014-150537.json"
      },
      "TaskName": "ReportGeneration",
      "StartTime": "2025-10-14T15:05:37.9659381+03:00",
      "Duration": 0.1646055,
      "Success": true,
      "Category": "Reporting",
      "Error": null,
      "Type": "Type1"
    }
  ],
  "ExecutionMode": "LIVE",
  "FailedTasks": 0,
  "TotalDuration": 0.1679546,
  "SuccessfulTasks": 10,
  "SessionStartTime": "2025-10-14T15:05:37.7450211+03:00",
  "Configuration": {
    "execution": {
      "defaultMode": "unattended",
      "countdownSeconds": 20,
      "enableDryRun": true,
      "autoSelectDefault": true,
      "showProgressBars": true
    },
    "modules": {
      "skipBloatwareRemoval": false,
      "skipEssentialApps": false,
      "skipWindowsUpdates": false,
      "skipTelemetryDisable": false,
      "skipSystemOptimization": false,
      "skipSecurityAudit": false,
      "customModulesPath": ""
    },
    "bloatware": {
      "enableDiffBasedProcessing": true,
      "parallelRemoval": true,
      "createBackups": true,
      "customBloatwareList": []
    },
    "essentialApps": {
      "enableParallelInstallation": true,
      "fallbackToLibreOffice": true,
      "customEssentialApps": [],
      "skipConflictResolution": false
    },
    "system": {
      "createSystemRestorePoint": true,
      "enableVerboseLogging": false,
      "maxLogSizeMB": 10,
      "enablePerformanceOptimizations": true
    },
    "reporting": {
      "enableHtmlReport": true,
      "enableDetailedAudit": true,
      "includeSystemInventory": true,
      "generateBeforeAfterComparison": true
    },
    "paths": {
      "tempFolder": "temp_files",
      "reportsFolder": "temp_files/reports",
      "logsFolder": "temp_files/logs",
      "inventoryFolder": "temp_files/inventory"
    }
  },
  "TasksExecuted": 1,
  "EndTime": "2025-10-14T15:05:38.1334949+03:00",
  "TaskExecutionStartTime": "2025-10-14T15:05:37.9633737+03:00"
}
